{
 "actions": [],
 "allow_rename": 1,
 "creation": "2024-07-03 17:41:08.454121",
 "doctype": "DocType",
 "editable_grid": 1,
 "engine": "InnoDB",
 "field_order": [
  "name1"
 ],
 "fields": [
  {
   "fieldname": "name1",
   "fieldtype": "Link",
   "in_list_view": 1,
   "label": "Name",
   "options": "Healthcare Practitioner"
  }
 ],
 "index_web_pages_for_search": 1,
 "istable": 1,
 "links": [],
 "modified": "2024-07-03 19:00:29.320856",
 "modified_by": "Administrator",
 "module": "Swissmedhealth",
 "name": "Practitioner",
 "owner": "Administrator",
 "permissions": [],
 "sort_field": "modified",
 "sort_order": "DESC",
 "states": []
}