{
 "actions": [],
 "creation": "2024-05-31 16:37:06.804671",
 "doctype": "DocType",
 "engine": "InnoDB",
 "field_order": [
  "totals_beds"
 ],
 "fields": [
  {
   "fieldname": "totals_beds",
   "fieldtype": "Link",
   "in_list_view": 1,
   "label": "Totals Beds",
   "options": "Totals Beds"
  }
 ],
 "index_web_pages_for_search": 1,
 "istable": 1,
 "links": [],
 "modified": "2024-05-31 17:30:43.980707",
 "modified_by": "Administrator",
 "module": "Swissmedhealth",
 "name": "Totals Beds Child",
 "owner": "Administrator",
 "permissions": [],
 "sort_field": "modified",
 "sort_order": "DESC",
 "states": []
}